drf_logto/__init__.py
drf_logto/admin.py
drf_logto/apps.py
drf_logto/backends.py
drf_logto/jwt_auth.py
drf_logto/models.py
drf_logto/settings.py
drf_logto/tests.py
drf_logto/urls.py
drf_logto/views.py
drf_logto-0.1.0.dist-info/LICENSE
drf_logto-0.1.0.dist-info/METADATA
drf_logto-0.1.0.dist-info/WHEEL
drf_logto-0.1.0.dist-info/RECORD
