Metadata-Version: 2.1
Name: drf-logto
Version: 0.1.0
Summary: Logto authentication integration for Django Rest Framework.
Home-page: https://github.com/housain-maina/drf-logto
License: MIT
Author: Hussaini Usman
Author-email: hussainmaina27@gmail.com
Requires-Python: >=3.9,<4.0
Classifier: License :: OSI Approved :: MIT License
Classifier: Programming Language :: Python :: 3
Classifier: Programming Language :: Python :: 3.9
Classifier: Programming Language :: Python :: 3.10
Classifier: Programming Language :: Python :: 3.11
Classifier: Programming Language :: Python :: 3.12
Requires-Dist: django (>=3.2)
Requires-Dist: djangorestframework (>=3.2)
Requires-Dist: djangorestframework-simplejwt (>=4.1)
